faculty_xval/__init__.py
faculty_xval/splitting.py
faculty_xval/utilities.py
faculty_xval/validation.py
faculty_xval/bin/__init__.py
faculty_xval/bin/jobs_cross_validation_executor.py
faculty_xval-0.1.0.dist-info/LICENSE-2.0.txt
faculty_xval-0.1.0.dist-info/METADATA
faculty_xval-0.1.0.dist-info/WHEEL
faculty_xval-0.1.0.dist-info/entry_points.txt
faculty_xval-0.1.0.dist-info/top_level.txt
faculty_xval-0.1.0.dist-info/RECORD
