Metadata-Version: 2.1
Name: faculty-xval
Version: 0.1.0
Summary: Cross validation of machine-learning models on Faculty platform.
Home-page: https://github.com/facultyai/faculty-xval
Author: Faculty
Author-email: info@faculty.ai
License: UNKNOWN
Platform: UNKNOWN
Requires-Dist: click
Requires-Dist: faculty
Requires-Dist: keras (>=2.2.4)
Requires-Dist: numpy
Requires-Dist: scikit-learn
Requires-Dist: tensorflow
